[
    {
        "courseCode": "LAT 101",
        "dist": [
            {
                "courseCode": "LAT 101",
                "courseCredits": "4",
                "courseDigit": 101,
                "courseNumber": "101",
                "credits": "4",
                "deptName": "World Languages & Literatures",
                "description": "First-Year Latin. Default description for First-Year Latin.",
                "displayTitle": "First-Year Latin Term 1",
                "id": "19842",
                "subjectCode": "LAT",
                "subjectDesc": "Latin",
                "years": [
                    {
                        "acayear": "2022-2023",
                        "terms": [
                            {
                                "active": true,
                                "cancelled": false,
                                "evenings": false,
                                "online": false,
                                "tentative": false,
                                "term": "FA",
                                "year": "2022",
                                "yearyy": "22"
                            },
                            {
                                "active": false,
                                "cancelled": false,
                                "evenings": false,
                                "online": false,
                                "tentative": false,
                                "term": "WI",
                                "year": "2023",
                                "yearyy": "23"
                            },
                            {
                                "active": false,
                                "cancelled": false,
                                "evenings": false,
                                "online": false,
                                "tentative": false,
                                "term": "SP",
                                "year": "2023",
                                "yearyy": "23"
                            },
                            {
                                "active": false,
                                "cancelled": false,
                                "evenings": false,
                                "online": false,
                                "tentative": false,
                                "term": "SU",
                                "year": "2023",
                                "yearyy": "23"
                            }
                        ],
                        "year": "2022"
                    },
                    {
                        "acayear": "2023-2024",
                        "terms": [
                            {
                                "active": true,
                                "cancelled": false,
                                "evenings": false,
                                "online": false,
                                "tentative": false,
                                "term": "FA",
                                "year": "2023",
                                "yearyy": "23"
                            },
                            {
                                "active": false,
                                "cancelled": false,
                                "evenings": false,
                                "online": false,
                                "tentative": false,
                                "term": "WI",
                                "year": "2024",
                                "yearyy": "24"
                            },
                            {
                                "active": false,
                                "cancelled": false,
                                "evenings": false,
                                "online": false,
                                "tentative": false,
                                "term": "SP",
                                "year": "2024",
                                "yearyy": "24"
                            },
                            {
                                "active": false,
                                "cancelled": false,
                                "evenings": false,
                                "online": false,
                                "tentative": false,
                                "term": "SU",
                                "year": "2024",
                                "yearyy": "24"
                            }
                        ],
                        "year": "2023"
                    },
                    {
                        "acayear": "2024-2025",
                        "terms": [
                            {
                                "active": true,
                                "cancelled": false,
                                "evenings": false,
                                "online": false,
                                "tentative": false,
                                "term": "FA",
                                "year": "2024",
                                "yearyy": "24"
                            },
                            {
                                "active": false,
                                "cancelled": false,
                                "evenings": false,
                                "online": false,
                                "tentative": false,
                                "term": "WI",
                                "year": "2025",
                                "yearyy": "25"
                            },
                            {
                                "active": false,
                                "cancelled": false,
                                "evenings": false,
                                "online": false,
                                "tentative": false,
                                "term": "SP",
                                "year": "2025",
                                "yearyy": "25"
                            },
                            {
                                "active": false,
                                "cancelled": false,
                                "evenings": false,
                                "online": false,
                                "tentative": false,
                                "term": "SU",
                                "year": "2025",
                                "yearyy": "25"
                            }
                        ],
                        "year": "2024"
                    }
                ]
            }
        ]
    },
    {
        "courseCode": "LAT 102",
        "dist": [
            {
                "courseCode": "LAT 102",
                "courseCredits": "4",
                "courseDigit": 102,
                "courseNumber": "102",
                "credits": "4",
                "deptName": "World Languages & Literatures",
                "description": "First-Year Latin. Default description for First-Year Latin.",
                "displayTitle": "First-Year Latin Term 2",
                "id": "19843",
                "subjectCode": "LAT",
                "subjectDesc": "Latin",
                "years": [
                    {
                        "acayear": "2022-2023",
                        "terms": [
                            {
                                "active": false,
                                "cancelled": false,
                                "evenings": false,
                                "online": false,
                                "tentative": false,
                                "term": "FA",
                                "year": "2022",
                                "yearyy": "22"
                            },
                            {
                                "active": true,
                                "cancelled": false,
                                "evenings": false,
                                "online": false,
                                "tentative": false,
                                "term": "WI",
                                "year": "2023",
                                "yearyy": "23"
                            },
                            {
                                "active": false,
                                "cancelled": false,
                                "evenings": false,
                                "online": false,
                                "tentative": false,
                                "term": "SP",
                                "year": "2023",
                                "yearyy": "23"
                            },
                            {
                                "active": false,
                                "cancelled": false,
                                "evenings": false,
                                "online": false,
                                "tentative": false,
                                "term": "SU",
                                "year": "2023",
                                "yearyy": "23"
                            }
                        ],
                        "year": "2022"
                    },
                    {
                        "acayear": "2023-2024",
                        "terms": [
                            {
                                "active": false,
                                "cancelled": false,
                                "evenings": false,
                                "online": false,
                                "tentative": false,
                                "term": "FA",
                                "year": "2023",
                                "yearyy": "23"
                            },
                            {
                                "active": true,
                                "cancelled": false,
                                "evenings": false,
                                "online": false,
                                "tentative": false,
                                "term": "WI",
                                "year": "2024",
                                "yearyy": "24"
                            },
                            {
                                "active": false,
                                "cancelled": false,
                                "evenings": false,
                                "online": false,
                                "tentative": false,
                                "term": "SP",
                                "year": "2024",
                                "yearyy": "24"
                            },
                            {
                                "active": false,
                                "cancelled": false,
                                "evenings": false,
                                "online": false,
                                "tentative": false,
                                "term": "SU",
                                "year": "2024",
                                "yearyy": "24"
                            }
                        ],
                        "year": "2023"
                    },
                    {
                        "acayear": "2024-2025",
                        "terms": [
                            {
                                "active": false,
                                "cancelled": false,
                                "evenings": false,
                                "online": false,
                                "tentative": false,
                                "term": "FA",
                                "year": "2024",
                                "yearyy": "24"
                            },
                            {
                                "active": true,
                                "cancelled": false,
                                "evenings": false,
                                "online": false,
                                "tentative": false,
                                "term": "WI",
                                "year": "2025",
                                "yearyy": "25"
                            },
                            {
                                "active": false,
                                "cancelled": false,
                                "evenings": false,
                                "online": false,
                                "tentative": false,
                                "term": "SP",
                                "year": "2025",
                                "yearyy": "25"
                            },
                            {
                                "active": false,
                                "cancelled": false,
                                "evenings": false,
                                "online": false,
                                "tentative": false,
                                "term": "SU",
                                "year": "2025",
                                "yearyy": "25"
                            }
                        ],
                        "year": "2024"
                    }
                ]
            }
        ]
    },
    {
        "courseCode": "LAT 103",
        "dist": [
            {
                "courseCode": "LAT 103",
                "courseCredits": "4",
                "courseDigit": 103,
                "courseNumber": "103",
                "credits": "4",
                "deptName": "World Languages & Literatures",
                "description": "First-Year Latin. Default description for First-Year Latin.",
                "displayTitle": "First-Year Latin Term 3",
                "id": "19844",
                "subjectCode": "LAT",
                "subjectDesc": "Latin",
                "years": [
                    {
                        "acayear": "2022-2023",
                        "terms": [
                            {
                                "active": false,
                                "cancelled": false,
                                "evenings": false,
                                "online": false,
                                "tentative": false,
                                "term": "FA",
                                "year": "2022",
                                "yearyy": "22"
                            },
                            {
                                "active": false,
                                "cancelled": false,
                                "evenings": false,
                                "online": false,
                                "tentative": false,
                                "term": "WI",
                                "year": "2023",
                                "yearyy": "23"
                            },
                            {
                                "active": true,
                                "cancelled": false,
                                "evenings": false,
                                "online": false,
                                "tentative": false,
                                "term": "SP",
                                "year": "2023",
                                "yearyy": "23"
                            },
                            {
                                "active": false,
                                "cancelled": false,
                                "evenings": false,
                                "online": false,
                                "tentative": false,
                                "term": "SU",
                                "year": "2023",
                                "yearyy": "23"
                            }
                        ],
                        "year": "2022"
                    },
                    {
                        "acayear": "2023-2024",
                        "terms": [
                            {
                                "active": false,
                                "cancelled": false,
                                "evenings": false,
                                "online": false,
                                "tentative": false,
                                "term": "FA",
                                "year": "2023",
                                "yearyy": "23"
                            },
                            {
                                "active": false,
                                "cancelled": false,
                                "evenings": false,
                                "online": false,
                                "tentative": false,
                                "term": "WI",
                                "year": "2024",
                                "yearyy": "24"
                            },
                            {
                                "active": true,
                                "cancelled": false,
                                "evenings": false,
                                "online": false,
                                "tentative": false,
                                "term": "SP",
                                "year": "2024",
                                "yearyy": "24"
                            },
                            {
                                "active": false,
                                "cancelled": false,
                                "evenings": false,
                                "online": false,
                                "tentative": false,
                                "term": "SU",
                                "year": "2024",
                                "yearyy": "24"
                            }
                        ],
                        "year": "2023"
                    },
                    {
                        "acayear": "2024-2025",
                        "terms": [
                            {
                                "active": false,
                                "cancelled": false,
                                "evenings": false,
                                "online": false,
                                "tentative": false,
                                "term": "FA",
                                "year": "2024",
                                "yearyy": "24"
                            },
                            {
                                "active": false,
                                "cancelled": false,
                                "evenings": false,
                                "online": false,
                                "tentative": false,
                                "term": "WI",
                                "year": "2025",
                                "yearyy": "25"
                            },
                            {
                                "active": true,
                                "cancelled": false,
                                "evenings": false,
                                "online": false,
                                "tentative": false,
                                "term": "SP",
                                "year": "2025",
                                "yearyy": "25"
                            },
                            {
                                "active": false,
                                "cancelled": false,
                                "evenings": false,
                                "online": false,
                                "tentative": false,
                                "term": "SU",
                                "year": "2025",
                                "yearyy": "25"
                            }
                        ],
                        "year": "2024"
                    }
                ]
            }
        ]
    },
    {
        "courseCode": "LAT 201",
        "dist": [
            {
                "courseCode": "LAT 201",
                "courseCredits": "4",
                "courseDigit": 201,
                "courseNumber": "201",
                "credits": "4",
                "deptName": "World Languages & Literatures",
                "description": "Second-Year Latin. Default description for Second-Year Latin.",
                "displayTitle": "Second-Year Latin Term 1",
                "id": "19845",
                "subjectCode": "LAT",
                "subjectDesc": "Latin",
                "years": [
                    {
                        "acayear": "2022-2023",
                        "terms": [
                            {
                                "active": true,
                                "cancelled": false,
                                "evenings": false,
                                "online": false,
                                "tentative": false,
                                "term": "FA",
                                "year": "2022",
                                "yearyy": "22"
                            },
                            {
                                "active": false,
                                "cancelled": false,
                                "evenings": false,
                                "online": false,
                                "tentative": false,
                                "term": "WI",
                                "year": "2023",
                                "yearyy": "23"
                            },
                            {
                                "active": false,
                                "cancelled": false,
                                "evenings": false,
                                "online": false,
                                "tentative": false,
                                "term": "SP",
                                "year": "2023",
                                "yearyy": "23"
                            },
                            {
                                "active": false,
                                "cancelled": false,
                                "evenings": false,
                                "online": false,
                                "tentative": false,
                                "term": "SU",
                                "year": "2023",
                                "yearyy": "23"
                            }
                        ],
                        "year": "2022"
                    },
                    {
                        "acayear": "2023-2024",
                        "terms": [
                            {
                                "active": true,
                                "cancelled": false,
                                "evenings": false,
                                "online": false,
                                "tentative": false,
                                "term": "FA",
                                "year": "2023",
                                "yearyy": "23"
                            },
                            {
                                "active": false,
                                "cancelled": false,
                                "evenings": false,
                                "online": false,
                                "tentative": false,
                                "term": "WI",
                                "year": "2024",
                                "yearyy": "24"
                            },
                            {
                                "active": false,
                                "cancelled": false,
                                "evenings": false,
                                "online": false,
                                "tentative": false,
                                "term": "SP",
                                "year": "2024",
                                "yearyy": "24"
                            },
                            {
                                "active": false,
                                "cancelled": false,
                                "evenings": false,
                                "online": false,
                                "tentative": false,
                                "term": "SU",
                                "year": "2024",
                                "yearyy": "24"
                            }
                        ],
                        "year": "2023"
                    },
                    {
                        "acayear": "2024-2025",
                        "terms": [
                            {
                                "active": true,
                                "cancelled": false,
                                "evenings": false,
                                "online": false,
                                "tentative": false,
                                "term": "FA",
                                "year": "2024",
                                "yearyy": "24"
                            },
                            {
                                "active": false,
                                "cancelled": false,
                                "evenings": false,
                                "online": false,
                                "tentative": false,
                                "term": "WI",
                                "year": "2025",
                                "yearyy": "25"
                            },
                            {
                                "active": false,
                                "cancelled": false,
                                "evenings": false,
                                "online": false,
                                "tentative": false,
                                "term": "SP",
                                "year": "2025",
                                "yearyy": "25"
                            },
                            {
                                "active": false,
                                "cancelled": false,
                                "evenings": false,
                                "online": false,
                                "tentative": false,
                                "term": "SU",
                                "year": "2025",
                                "yearyy": "25"
                            }
                        ],
                        "year": "2024"
                    }
                ]
            }
        ]
    },
    {
        "courseCode": "LAT 202",
        "dist": [
            {
                "courseCode": "LAT 202",
                "courseCredits": "4",
                "courseDigit": 202,
                "courseNumber": "202",
                "credits": "4",
                "deptName": "World Languages & Literatures",
                "description": "Second-Year Latin. Default description for Second-Year Latin.",
                "displayTitle": "Second-Year Latin Term 2",
                "id": "19846",
                "subjectCode": "LAT",
                "subjectDesc": "Latin",
                "years": [
                    {
                        "acayear": "2022-2023",
                        "terms": [
                            {
                                "active": false,
                                "cancelled": false,
                                "evenings": false,
                                "online": false,
                                "tentative": false,
                                "term": "FA",
                                "year": "2022",
                                "yearyy": "22"
                            },
                            {
                                "active": true,
                                "cancelled": false,
                                "evenings": false,
                                "online": false,
                                "tentative": false,
                                "term": "WI",
                                "year": "2023",
                                "yearyy": "23"
                            },
                            {
                                "active": false,
                                "cancelled": false,
                                "evenings": false,
                                "online": false,
                                "tentative": false,
                                "term": "SP",
                                "year": "2023",
                                "yearyy": "23"
                            },
                            {
                                "active": false,
                                "cancelled": false,
                                "evenings": false,
                                "online": false,
                                "tentative": false,
                                "term": "SU",
                                "year": "2023",
                                "yearyy": "23"
                            }
                        ],
                        "year": "2022"
                    },
                    {
                        "acayear": "2023-2024",
                        "terms": [
                            {
                                "active": false,
                                "cancelled": false,
                                "evenings": false,
                                "online": false,
                                "tentative": false,
                                "term": "FA",
                                "year": "2023",
                                "yearyy": "23"
                            },
                            {
                                "active": true,
                                "cancelled": false,
                                "evenings": false,
                                "online": false,
                                "tentative": false,
                                "term": "WI",
                                "year": "2024",
                                "yearyy": "24"
                            },
                            {
                                "active": false,
                                "cancelled": false,
                                "evenings": false,
                                "online": false,
                                "tentative": false,
                                "term": "SP",
                                "year": "2024",
                                "yearyy": "24"
                            },
                            {
                                "active": false,
                                "cancelled": false,
                                "evenings": false,
                                "online": false,
                                "tentative": false,
                                "term": "SU",
                                "year": "2024",
                                "yearyy": "24"
                            }
                        ],
                        "year": "2023"
                    },
                    {
                        "acayear": "2024-2025",
                        "terms": [
                            {
                                "active": false,
                                "cancelled": false,
                                "evenings": false,
                                "online": false,
                                "tentative": false,
                                "term": "FA",
                                "year": "2024",
                                "yearyy": "24"
                            },
                            {
                                "active": true,
                                "cancelled": false,
                                "evenings": false,
                                "online": false,
                                "tentative": false,
                                "term": "WI",
                                "year": "2025",
                                "yearyy": "25"
                            },
                            {
                                "active": false,
                                "cancelled": false,
                                "evenings": false,
                                "online": false,
                                "tentative": false,
                                "term": "SP",
                                "year": "2025",
                                "yearyy": "25"
                            },
                            {
                                "active": false,
                                "cancelled": false,
                                "evenings": false,
                                "online": false,
                                "tentative": false,
                                "term": "SU",
                                "year": "2025",
                                "yearyy": "25"
                            }
                        ],
                        "year": "2024"
                    }
                ]
            }
        ]
    },
    {
        "courseCode": "LAT 203",
        "dist": [
            {
                "courseCode": "LAT 203",
                "courseCredits": "4",
                "courseDigit": 203,
                "courseNumber": "203",
                "credits": "4",
                "deptName": "World Languages & Literatures",
                "description": "Second-Year Latin. Default description for Second-Year Latin.",
                "displayTitle": "Second-Year Latin Term 3",
                "id": "19847",
                "subjectCode": "LAT",
                "subjectDesc": "Latin",
                "years": [
                    {
                        "acayear": "2022-2023",
                        "terms": [
                            {
                                "active": false,
                                "cancelled": false,
                                "evenings": false,
                                "online": false,
                                "tentative": false,
                                "term": "FA",
                                "year": "2022",
                                "yearyy": "22"
                            },
                            {
                                "active": false,
                                "cancelled": false,
                                "evenings": false,
                                "online": false,
                                "tentative": false,
                                "term": "WI",
                                "year": "2023",
                                "yearyy": "23"
                            },
                            {
                                "active": true,
                                "cancelled": false,
                                "evenings": false,
                                "online": false,
                                "tentative": false,
                                "term": "SP",
                                "year": "2023",
                                "yearyy": "23"
                            },
                            {
                                "active": false,
                                "cancelled": false,
                                "evenings": false,
                                "online": false,
                                "tentative": false,
                                "term": "SU",
                                "year": "2023",
                                "yearyy": "23"
                            }
                        ],
                        "year": "2022"
                    },
                    {
                        "acayear": "2023-2024",
                        "terms": [
                            {
                                "active": false,
                                "cancelled": false,
                                "evenings": false,
                                "online": false,
                                "tentative": false,
                                "term": "FA",
                                "year": "2023",
                                "yearyy": "23"
                            },
                            {
                                "active": false,
                                "cancelled": false,
                                "evenings": false,
                                "online": false,
                                "tentative": false,
                                "term": "WI",
                                "year": "2024",
                                "yearyy": "24"
                            },
                            {
                                "active": true,
                                "cancelled": false,
                                "evenings": false,
                                "online": false,
                                "tentative": false,
                                "term": "SP",
                                "year": "2024",
                                "yearyy": "24"
                            },
                            {
                                "active": false,
                                "cancelled": false,
                                "evenings": false,
                                "online": false,
                                "tentative": false,
                                "term": "SU",
                                "year": "2024",
                                "yearyy": "24"
                            }
                        ],
                        "year": "2023"
                    },
                    {
                        "acayear": "2024-2025",
                        "terms": [
                            {
                                "active": false,
                                "cancelled": false,
                                "evenings": false,
                                "online": false,
                                "tentative": false,
                                "term": "FA",
                                "year": "2024",
                                "yearyy": "24"
                            },
                            {
                                "active": false,
                                "cancelled": false,
                                "evenings": false,
                                "online": false,
                                "tentative": false,
                                "term": "WI",
                                "year": "2025",
                                "yearyy": "25"
                            },
                            {
                                "active": true,
                                "cancelled": false,
                                "evenings": false,
                                "online": false,
                                "tentative": false,
                                "term": "SP",
                                "year": "2025",
                                "yearyy": "25"
                            },
                            {
                                "active": false,
                                "cancelled": false,
                                "evenings": false,
                                "online": false,
                                "tentative": false,
                                "term": "SU",
                                "year": "2025",
                                "yearyy": "25"
                            }
                        ],
                        "year": "2024"
                    }
                ]
            }
        ]
    },
    {
        "courseCode": "LAT 330U",
        "dist": [
            {
                "courseCode": "LAT 330U",
                "courseCredits": "4",
                "courseDigit": 330,
                "courseNumber": "330U",
                "credits": "4",
                "deptName": "World Languages & Literatures",
                "description": null,
                "displayTitle": "Roman Culture",
                "id": "10266",
                "subjectCode": "LAT",
                "subjectDesc": "Latin",
                "years": [
                    {
                        "acayear": "2022-2023",
                        "terms": [
                            {
                                "active": false,
                                "cancelled": false,
                                "evenings": false,
                                "online": false,
                                "tentative": false,
                                "term": "FA",
                                "year": "2022",
                                "yearyy": "22"
                            },
                            {
                                "active": true,
                                "cancelled": false,
                                "evenings": false,
                                "online": false,
                                "tentative": false,
                                "term": "WI",
                                "year": "2023",
                                "yearyy": "23"
                            },
                            {
                                "active": false,
                                "cancelled": false,
                                "evenings": false,
                                "online": false,
                                "tentative": false,
                                "term": "SP",
                                "year": "2023",
                                "yearyy": "23"
                            },
                            {
                                "active": false,
                                "cancelled": false,
                                "evenings": false,
                                "online": false,
                                "tentative": false,
                                "term": "SU",
                                "year": "2023",
                                "yearyy": "23"
                            }
                        ],
                        "year": "2022"
                    },
                    {
                        "acayear": "2023-2024",
                        "terms": [
                            {
                                "active": false,
                                "cancelled": false,
                                "evenings": false,
                                "online": false,
                                "tentative": false,
                                "term": "FA",
                                "year": "2023",
                                "yearyy": "23"
                            },
                            {
                                "active": true,
                                "cancelled": false,
                                "evenings": false,
                                "online": false,
                                "tentative": false,
                                "term": "WI",
                                "year": "2024",
                                "yearyy": "24"
                            },
                            {
                                "active": false,
                                "cancelled": false,
                                "evenings": false,
                                "online": false,
                                "tentative": false,
                                "term": "SP",
                                "year": "2024",
                                "yearyy": "24"
                            },
                            {
                                "active": false,
                                "cancelled": false,
                                "evenings": false,
                                "online": false,
                                "tentative": false,
                                "term": "SU",
                                "year": "2024",
                                "yearyy": "24"
                            }
                        ],
                        "year": "2023"
                    },
                    {
                        "acayear": "2024-2025",
                        "terms": [
                            {
                                "active": false,
                                "cancelled": false,
                                "evenings": false,
                                "online": false,
                                "tentative": false,
                                "term": "FA",
                                "year": "2024",
                                "yearyy": "24"
                            },
                            {
                                "active": true,
                                "cancelled": false,
                                "evenings": false,
                                "online": false,
                                "tentative": false,
                                "term": "WI",
                                "year": "2025",
                                "yearyy": "25"
                            },
                            {
                                "active": false,
                                "cancelled": false,
                                "evenings": false,
                                "online": false,
                                "tentative": false,
                                "term": "SP",
                                "year": "2025",
                                "yearyy": "25"
                            },
                            {
                                "active": false,
                                "cancelled": false,
                                "evenings": false,
                                "online": false,
                                "tentative": false,
                                "term": "SU",
                                "year": "2025",
                                "yearyy": "25"
                            }
                        ],
                        "year": "2024"
                    }
                ]
            }
        ]
    },
    {
        "courseCode": "LAT 341U",
        "dist": [
            {
                "courseCode": "LAT 341U",
                "courseCredits": "4",
                "courseDigit": 341,
                "courseNumber": "341U",
                "credits": "4",
                "deptName": "World Languages & Literatures",
                "description": null,
                "displayTitle": "Roman Literature in Translation",
                "id": "10268",
                "subjectCode": "LAT",
                "subjectDesc": "Latin",
                "years": [
                    {
                        "acayear": "2022-2023",
                        "terms": [
                            {
                                "active": false,
                                "cancelled": false,
                                "evenings": false,
                                "online": false,
                                "tentative": false,
                                "term": "FA",
                                "year": "2022",
                                "yearyy": "22"
                            },
                            {
                                "active": false,
                                "cancelled": false,
                                "evenings": false,
                                "online": false,
                                "tentative": false,
                                "term": "WI",
                                "year": "2023",
                                "yearyy": "23"
                            },
                            {
                                "active": true,
                                "cancelled": false,
                                "evenings": false,
                                "online": false,
                                "tentative": false,
                                "term": "SP",
                                "year": "2023",
                                "yearyy": "23"
                            },
                            {
                                "active": false,
                                "cancelled": false,
                                "evenings": false,
                                "online": false,
                                "tentative": false,
                                "term": "SU",
                                "year": "2023",
                                "yearyy": "23"
                            }
                        ],
                        "year": "2022"
                    },
                    {
                        "acayear": "2023-2024",
                        "terms": [
                            {
                                "active": false,
                                "cancelled": false,
                                "evenings": false,
                                "online": false,
                                "tentative": false,
                                "term": "FA",
                                "year": "2023",
                                "yearyy": "23"
                            },
                            {
                                "active": false,
                                "cancelled": false,
                                "evenings": false,
                                "online": false,
                                "tentative": false,
                                "term": "WI",
                                "year": "2024",
                                "yearyy": "24"
                            },
                            {
                                "active": true,
                                "cancelled": false,
                                "evenings": false,
                                "online": false,
                                "tentative": false,
                                "term": "SP",
                                "year": "2024",
                                "yearyy": "24"
                            },
                            {
                                "active": false,
                                "cancelled": false,
                                "evenings": false,
                                "online": false,
                                "tentative": false,
                                "term": "SU",
                                "year": "2024",
                                "yearyy": "24"
                            }
                        ],
                        "year": "2023"
                    },
                    {
                        "acayear": "2024-2025",
                        "terms": [
                            {
                                "active": false,
                                "cancelled": false,
                                "evenings": false,
                                "online": false,
                                "tentative": false,
                                "term": "FA",
                                "year": "2024",
                                "yearyy": "24"
                            },
                            {
                                "active": false,
                                "cancelled": false,
                                "evenings": false,
                                "online": false,
                                "tentative": false,
                                "term": "WI",
                                "year": "2025",
                                "yearyy": "25"
                            },
                            {
                                "active": true,
                                "cancelled": false,
                                "evenings": false,
                                "online": false,
                                "tentative": false,
                                "term": "SP",
                                "year": "2025",
                                "yearyy": "25"
                            },
                            {
                                "active": false,
                                "cancelled": false,
                                "evenings": false,
                                "online": false,
                                "tentative": false,
                                "term": "SU",
                                "year": "2025",
                                "yearyy": "25"
                            }
                        ],
                        "year": "2024"
                    }
                ]
            }
        ]
    }
]